odoo/addons/project_purchase_analytic_global/README.rst
odoo/addons/project_purchase_analytic_global/__init__.py
odoo/addons/project_purchase_analytic_global/__manifest__.py
odoo/addons/project_purchase_analytic_global/i18n/es.po
odoo/addons/project_purchase_analytic_global/i18n/it.po
odoo/addons/project_purchase_analytic_global/i18n/project_purchase_analytic_global.pot
odoo/addons/project_purchase_analytic_global/models/__init__.py
odoo/addons/project_purchase_analytic_global/models/project.py
odoo/addons/project_purchase_analytic_global/models/purchase_order_line.py
odoo/addons/project_purchase_analytic_global/readme/CONTRIBUTORS.rst
odoo/addons/project_purchase_analytic_global/readme/DESCRIPTION.rst
odoo/addons/project_purchase_analytic_global/static/description/icon.png
odoo/addons/project_purchase_analytic_global/static/description/index.html
odoo/addons/project_purchase_analytic_global/tests/__init__.py
odoo/addons/project_purchase_analytic_global/tests/test_project_purchase_analytic_global.py
odoo_addon_project_purchase_analytic_global-15.0.1.0.1.8.dist-info/METADATA
odoo_addon_project_purchase_analytic_global-15.0.1.0.1.8.dist-info/WHEEL
odoo_addon_project_purchase_analytic_global-15.0.1.0.1.8.dist-info/top_level.txt
odoo_addon_project_purchase_analytic_global-15.0.1.0.1.8.dist-info/RECORD
