Metadata-Version: 2.1
Name: odoo-addon-project-purchase-analytic-global
Version: 15.0.1.0.1.8
Summary: Project - Create Purchase Orders with Analytic Account
Home-page: https://github.com/OCA/project
Author: Camptocamp, Odoo Community Association (OCA)
Author-email: support@odoo-community.org
License: AGPL-3
Platform: UNKNOWN
Classifier: Programming Language :: Python
Classifier: Framework :: Odoo
Classifier: Framework :: Odoo :: 15.0
Classifier: License :: OSI Approved :: GNU Affero General Public License v3
Requires-Python: >=3.8
Requires-Dist: odoo-addon-purchase-analytic-global <15.1dev,>=15.0dev
Requires-Dist: odoo <15.1dev,>=15.0a
